spaceengineers/__init__.py
spaceengineers/api.py
spaceengineers/communication.py
spaceengineers/models.py
spaceengineers/proxy.py
space_engineers_iv4xr-0.0.1b0.dist-info/METADATA
space_engineers_iv4xr-0.0.1b0.dist-info/WHEEL
space_engineers_iv4xr-0.0.1b0.dist-info/RECORD
