Metadata-Version: 2.1
Name: space_engineers_iv4xr
Version: 0.0.1b0
Summary: Client for iv4XR Space Engineers plugin.
Project-URL: Homepage, https://github.com/iv4xr-project/iv4xr-se-plugin/PythonClient
Project-URL: Bug Tracker, https://github.com/iv4xr-project/iv4xr-se-plugin/issues
Project-URL: Space Engineers Plugin, https://github.com/iv4xr-project/iv4xr-se-plugin/
Project-URL: iv4XR project, https://iv4xr-project.eu/
Author-email: Karel Hovorka <karel.hovorka@goodai.com>
Maintainer-email: Karel Hovorka <se@karel-hovorka.eu>
Keywords: Space Engineers,automation,iv4XR
Classifier: Development Status :: 4 - Beta
Classifier: License :: OSI Approved :: GNU Lesser General Public License v3 (LGPLv3)
Classifier: Operating System :: OS Independent
Classifier: Programming Language :: Python :: 3
Classifier: Topic :: Games/Entertainment
Classifier: Topic :: Software Development :: Testing
Requires-Python: >=3
